autosv/__init__.py
autosv/autosv.py
autosv/cli.py
autosv/calculate/__init__.py
autosv/calculate/selection.py
autosv/calculate/sliding_cpu.py
autosv/calculate/sliding_gpu.py
autosv/log/__init__.py
autosv/log/logger.py
autosv/slice/__init__.py
autosv/slice/slice_video.py
autosv-0.0.3.dist-info/METADATA
autosv-0.0.3.dist-info/WHEEL
autosv-0.0.3.dist-info/entry_points.txt
autosv-0.0.3.dist-info/licenses/LICENSE
autosv-0.0.3.dist-info/RECORD
