Metadata-Version: 2.4
Name: autosv
Version: 0.0.3
Summary: Auto slice the highlight shorts based on the density of danmaku.
Project-URL: Homepage, https://github.com/timerring/auto-slice-video
Author: timerring
License: MIT License
License-File: LICENSE
Classifier: License :: OSI Approved :: MIT License
Classifier: Operating System :: OS Independent
Classifier: Programming Language :: Python :: 3
Requires-Python: >=3.7
Requires-Dist: numba>=0.55.1
Requires-Dist: numpy>=1.21.6
